ssterm.py
ssterm-3.0.0.dist-info/DESCRIPTION.rst
ssterm-3.0.0.dist-info/METADATA
ssterm-3.0.0.dist-info/RECORD
ssterm-3.0.0.dist-info/WHEEL
ssterm-3.0.0.dist-info/entry_points.txt
ssterm-3.0.0.dist-info/metadata.json
ssterm-3.0.0.dist-info/top_level.txt
